<?xml version="1.0" encoding="utf-8"?>
<dataroot xmlns:od="urn:schemas-microsoft-com:officedata" xmlns:xsi="http://www.w3.org/2001/XMLSchema-instance" xsi:noNamespaceSchemaLocation="Notentisch.xsd" generated="2026-01-29T14:11:13">
  <Notentisch>
    <NotID>532</NotID>
    <ArbeitsStatus>Zurück</ArbeitsStatus>
    <Speicherort>Tölzer Schützenmarsch  #..\..\myMusic\Noten\Blätter\Tölzer Schützenmarsch  .pdf#</Speicherort>
    <img>Cards_Export/card_532.png</img>
  </Notentisch>
  <Notentisch>
    <NotID>1</NotID>
    <ArbeitsStatus>gelernt</ArbeitsStatus>
    <Speicherort>Auf der Zwieselalm#..\..\myMusic\Noten\Blätter\Auf der Zwieselalm.pdf#</Speicherort>
    <img>Cards_Export/card_1.png</img>
  </Notentisch>
  <Notentisch>
    <NotID>17</NotID>
    <ArbeitsStatus>wiedervorlegen</ArbeitsStatus>
    <Speicherort>Links der Isar, rechts der Donau #..\..\myMusic\Noten\Blätter\Links der Isar, rechts der Donau .pdf#</Speicherort>
    <img>Cards_Export/card_17.png</img>
  </Notentisch>
  <Notentisch>
    <NotID>19</NotID>
    <ArbeitsStatus>Zurück</ArbeitsStatus>
    <Speicherort>An der schönen grünen Isar#..\..\myMusic\Noten\Blätter\An der schönen grünen Isar.pdf#</Speicherort>
    <img>Cards_Export/card_19.png</img>
  </Notentisch>
  <Notentisch>
    <NotID>22</NotID>
    <ArbeitsStatus>gelernt</ArbeitsStatus>
    <Speicherort>Die Veilchen vom Kochelsee#..\..\myMusic\Noten\Blätter\Die Veilchen vom Kochelsee.pdf#</Speicherort>
    <img>Cards_Export/card_22.png</img>
  </Notentisch>
  <Notentisch>
    <NotID>23</NotID>
    <ArbeitsStatus>gelernt</ArbeitsStatus>
    <Speicherort>Drunter und drüber #..\..\myMusic\Noten\Blätter\Drunter und drüber .pdf#</Speicherort>
    <img>Cards_Export/card_23.png</img>
  </Notentisch>
  <Notentisch>
    <NotID>35</NotID>
    <ArbeitsStatus>wiederholen</ArbeitsStatus>
    <Speicherort>Erinnerung an München #..\..\myMusic\Noten\Blätter\Erinnerung an München .pdf#</Speicherort>
    <img>Cards_Export/card_35.png</img>
  </Notentisch>
  <Notentisch>
    <NotID>44</NotID>
    <ArbeitsStatus>wiedervorlegen</ArbeitsStatus>
    <Speicherort>Froh und frei#..\..\myMusic\Noten\Blätter\Froh und frei.pdf#</Speicherort>
    <img>Cards_Export/card_44.png</img>
  </Notentisch>
  <Notentisch>
    <NotID>45</NotID>
    <ArbeitsStatus>Zurück</ArbeitsStatus>
    <Speicherort>Glockenblumen -Walzer#..\..\myMusic\Noten\Blätter\Glockenblumen -Walzer.pdf#</Speicherort>
    <img>Cards_Export/card_45.png</img>
  </Notentisch>
  <Notentisch>
    <NotID>50</NotID>
    <ArbeitsStatus>Zurück</ArbeitsStatus>
    <Speicherort>Blumen aus Bayern   #..\..\myMusic\Noten\Blätter\Blumen aus Bayern   .pdf#</Speicherort>
    <img>Cards_Export/card_50.png</img>
  </Notentisch>
  <Notentisch>
    <NotID>54</NotID>
    <ArbeitsStatus>gelernt</ArbeitsStatus>
    <Speicherort>Der Weg zum Herzen#..\..\myMusic\Noten\Blätter\Der Weg zum Herzen.pdf#</Speicherort>
    <img>Cards_Export/card_54.png</img>
  </Notentisch>
  <Notentisch>
    <NotID>61</NotID>
    <ArbeitsStatus>wiederholen</ArbeitsStatus>
    <Speicherort>Eroberte Herzen    #..\..\myMusic\Noten\Blätter\Eroberte Herzen    .pdf#</Speicherort>
    <img>Cards_Export/card_61.png</img>
  </Notentisch>
  <Notentisch>
    <NotID>71</NotID>
    <ArbeitsStatus>gelernt</ArbeitsStatus>
    <Speicherort>Stammcafe.pdf#C:\Users\User\OneDrive\myMusic\Noten\Blätter\Stammcafe.pdf#</Speicherort>
    <img>Cards_Export/card_71.png</img>
  </Notentisch>
  <Notentisch>
    <NotID>76</NotID>
    <ArbeitsStatus>wiederholen</ArbeitsStatus>
    <Speicherort>Straubinger Madln#..\..\myMusic\Noten\Blätter\Straubinger%20Madln.pdf#</Speicherort>
    <img>Cards_Export/card_76.png</img>
  </Notentisch>
  <Notentisch>
    <NotID>123</NotID>
    <ArbeitsStatus>Zurück</ArbeitsStatus>
    <Speicherort>Tiroler Buam#..\..\myMusic\Noten\Blätter\Tiroler Buam.pdf#</Speicherort>
    <img>Cards_Export/card_123.png</img>
  </Notentisch>
  <Notentisch>
    <NotID>185</NotID>
    <ArbeitsStatus>wiedervorlegen</ArbeitsStatus>
    <Speicherort>wie's von der Alm klingt#..\..\myMusic\Noten\Blätter\wie's von der Alm klingt.pdf#</Speicherort>
    <img>Cards_Export/card_185.png</img>
  </Notentisch>
  <Notentisch>
    <NotID>199</NotID>
    <ArbeitsStatus>wiedervorlegen</ArbeitsStatus>
    <Speicherort>Mit Herz und Hand fürs Alpenland#..\..\myMusic\Noten\Blätter\Mit Herz und Hand fürs Alpenland.pdf#</Speicherort>
    <img>Cards_Export/card_199.png</img>
  </Notentisch>
  <Notentisch>
    <NotID>301</NotID>
    <ArbeitsStatus>Zurück</ArbeitsStatus>
    <Speicherort>Ein Morgen am Traunsee#..\..\myMusic\Noten\Blätter\Ein Morgen am Traunsee.pdf#</Speicherort>
    <img>Cards_Export/card_301.png</img>
  </Notentisch>
  <Notentisch>
    <NotID>315</NotID>
    <ArbeitsStatus>gelernt</ArbeitsStatus>
    <Speicherort>Lachendes München#..\..\myMusic\Noten\Blätter\Lachendes München.pdf#</Speicherort>
    <img>Cards_Export/card_315.png</img>
  </Notentisch>
  <Notentisch>
    <NotID>335</NotID>
    <ArbeitsStatus>Zurück</ArbeitsStatus>
    <Speicherort>Bierlackerl Boarischer#..\..\myMusic\Noten\Blätter\Bierlackerl Boarischer.pdf#</Speicherort>
    <img>Cards_Export/card_335.png</img>
  </Notentisch>
  <Notentisch>
    <NotID>345</NotID>
    <ArbeitsStatus>wiedervorlegen</ArbeitsStatus>
    <Speicherort>Heut kommen d'Engerln auf Urlaub nach Wean#..\..\myMusic\Noten\Blätter\Heut kommen d'Engerln auf Urlaub nach Wean.pdf#</Speicherort>
    <img>Cards_Export/card_345.png</img>
  </Notentisch>
  <Notentisch>
    <NotID>355</NotID>
    <ArbeitsStatus>wiederholen</ArbeitsStatus>
    <Speicherort>Glocken der Heimat#..\..\myMusic\Noten\Blätter\Glocken der Heimat.pdf#</Speicherort>
    <img>Cards_Export/card_355.png</img>
  </Notentisch>
  <Notentisch>
    <NotID>360</NotID>
    <ArbeitsStatus>neueIdee</ArbeitsStatus>
    <Speicherort>Du und ich#..\..\myMusic\Noten\Blätter\Du und ich.pdf#</Speicherort>
    <img>Cards_Export/card_360.png</img>
  </Notentisch>
  <Notentisch>
    <NotID>363</NotID>
    <ArbeitsStatus>wiedervorlegen</ArbeitsStatus>
    <Speicherort>Alpenecho.pdf#C:\Users\User\OneDrive\myMusic\Noten\Blätter\Alpenecho.pdf#</Speicherort>
    <img>Cards_Export/card_363.png</img>
  </Notentisch>
  <Notentisch>
    <NotID>380</NotID>
    <ArbeitsStatus>Zurück</ArbeitsStatus>
    <Speicherort>Beim Mohrenwirt#..\..\myMusic\Noten\Blätter\Beim Mohrenwirt.pdf#</Speicherort>
    <img>Cards_Export/card_380.png</img>
  </Notentisch>
  <Notentisch>
    <NotID>387</NotID>
    <ArbeitsStatus>neueIdee</ArbeitsStatus>
    <Speicherort>Bergfrühling#..\..\myMusic\Noten\Blätter\Bergfrühling.pdf#</Speicherort>
    <img>Cards_Export/card_387.png</img>
  </Notentisch>
  <Notentisch>
    <NotID>389</NotID>
    <ArbeitsStatus>wiedervorlegen</ArbeitsStatus>
    <Speicherort>Aus dem Chiemgau#..\..\myMusic\Noten\Blätter\Aus dem Chiemgau.pdf#</Speicherort>
    <img>Cards_Export/card_389.png</img>
  </Notentisch>
  <Notentisch>
    <NotID>410</NotID>
    <ArbeitsStatus>wiedervorlegen</ArbeitsStatus>
    <Speicherort>Erinnerung#..\..\myMusic\Noten\Blätter\Erinnerung.pdf#</Speicherort>
    <img>Cards_Export/card_410.png</img>
  </Notentisch>
  <Notentisch>
    <NotID>434</NotID>
    <ArbeitsStatus>neueIdee</ArbeitsStatus>
    <Speicherort>Froh und heiter.pdf#C:\Users\User\OneDrive\myMusic\Noten\Blätter\Froh und heiter.pdf#</Speicherort>
    <img>Cards_Export/card_434.png</img>
  </Notentisch>
  <Notentisch>
    <NotID>449</NotID>
    <ArbeitsStatus>Zurück</ArbeitsStatus>
    <Speicherort>Picknick im Isartal#..\..\myMusic\Noten\Blätter\Picknick im Isartal.pdf#</Speicherort>
    <img>Cards_Export/card_449.png</img>
  </Notentisch>
  <Notentisch>
    <NotID>451</NotID>
    <ArbeitsStatus>wiedervorlegen</ArbeitsStatus>
    <Speicherort>Ja, ja der Wein ist gut#..\..\myMusic\Noten\Blätter\Ja, ja der Wein ist gut.pdf#</Speicherort>
    <img>Cards_Export/card_451.png</img>
  </Notentisch>
  <Notentisch>
    <NotID>453</NotID>
    <ArbeitsStatus>wiedervorlegen</ArbeitsStatus>
    <Speicherort>Stoiber Marsch#..\..\myMusic\Noten\Blätter\Stoiber Marsch.pdf#</Speicherort>
    <img>Cards_Export/card_453.png</img>
  </Notentisch>
  <Notentisch>
    <NotID>456</NotID>
    <ArbeitsStatus>gelernt</ArbeitsStatus>
    <Speicherort>Auf der Zwieselalm1#..\..\myMusic\Noten\Blätter\Auf der Zwieselalm1.pdf#</Speicherort>
    <img>Cards_Export/card_456.png</img>
  </Notentisch>
  <Notentisch>
    <NotID>457</NotID>
    <ArbeitsStatus>gelernt</ArbeitsStatus>
    <Speicherort>Fidele Schützen#..\..\myMusic\Noten\Blätter\Fidele Schützen.pdf#</Speicherort>
    <img>Cards_Export/card_457.png</img>
  </Notentisch>
  <Notentisch>
    <NotID>463</NotID>
    <ArbeitsStatus>neueIdee</ArbeitsStatus>
    <Speicherort>Heimatglocken#..\..\myMusic\Noten\Blätter\Heimatglocken.pdf#</Speicherort>
    <img>Cards_Export/card_463.png</img>
  </Notentisch>
  <Notentisch>
    <NotID>466</NotID>
    <ArbeitsStatus>Zurück</ArbeitsStatus>
    <Speicherort>Capri Fischer#..\..\myMusic\Noten\Unterhaltung und Stimmung\Capri Fischer.pdf#</Speicherort>
    <img>Cards_Export/card_466.png</img>
  </Notentisch>
  <Notentisch>
    <NotID>470</NotID>
    <ArbeitsStatus>neueIdee</ArbeitsStatus>
    <Speicherort>..\..\myMusic\Noten\Unterhaltung und Stimmung\ein schöner Tag.pdf#..\..\myMusic\Noten\Unterhaltung und Stimmung\ein schöner Tag.pdf#</Speicherort>
    <img>Cards_Export/card_470.png</img>
  </Notentisch>
  <Notentisch>
    <NotID>473</NotID>
    <ArbeitsStatus>neueIdee</ArbeitsStatus>
    <Speicherort>..\..\myMusic\Noten\Unterhaltung und Stimmung\oh! lady mary.pdf#..\..\myMusic\Noten\Unterhaltung und Stimmung\oh! lady mary.pdf#</Speicherort>
    <img>Cards_Export/card_473.png</img>
  </Notentisch>
  <Notentisch>
    <NotID>474</NotID>
    <ArbeitsStatus>neueIdee</ArbeitsStatus>
    <Speicherort>..\..\myMusic\Noten\Unterhaltung und Stimmung\que sera sera.pdf#..\..\myMusic\Noten\Unterhaltung und Stimmung\que sera sera.pdf#</Speicherort>
    <img>Cards_Export/card_474.png</img>
  </Notentisch>
  <Notentisch>
    <NotID>475</NotID>
    <ArbeitsStatus>neueIdee</ArbeitsStatus>
    <Speicherort>..\..\myMusic\Noten\Unterhaltung und Stimmung\seemann.pdf#..\..\myMusic\Noten\Unterhaltung und Stimmung\seemann.pdf#</Speicherort>
    <img>Cards_Export/card_475.png</img>
  </Notentisch>
  <Notentisch>
    <NotID>477</NotID>
    <ArbeitsStatus>neueIdee</ArbeitsStatus>
    <Speicherort>..\..\myMusic\Noten\Unterhaltung und Stimmung\tanze mit mir in den morgen Tango.pdf#..\..\myMusic\Noten\Unterhaltung und Stimmung\tanze mit mir in den morgen Tango.pdf#</Speicherort>
    <img>Cards_Export/card_477.png</img>
  </Notentisch>
  <Notentisch>
    <NotID>480</NotID>
    <ArbeitsStatus>Zurück</ArbeitsStatus>
    <Speicherort>..\..\myMusic\Noten\Unterhaltung und Stimmung\wenn der weisse flieder .pdf#..\..\myMusic\Noten\Unterhaltung und Stimmung\wenn der weisse flieder .pdf#</Speicherort>
    <img>Cards_Export/card_480.png</img>
  </Notentisch>
  <Notentisch>
    <NotID>486</NotID>
    <ArbeitsStatus>gelernt</ArbeitsStatus>
    <Speicherort>Stachuspolka#..\..\myMusic\Noten\Blätter\Stachuspolka.pdf#</Speicherort>
    <img>Cards_Export/card_486.png</img>
  </Notentisch>
  <Notentisch>
    <NotID>519</NotID>
    <ArbeitsStatus>wiedervorlegen</ArbeitsStatus>
    <Speicherort>Wheels#..\..\myMusic\Noten\Blätter\Wheels.pdf#</Speicherort>
    <img>Cards_Export/card_519.png</img>
  </Notentisch>
  <Notentisch>
    <NotID>520</NotID>
    <ArbeitsStatus>gelernt</ArbeitsStatus>
    <Speicherort>Stachuspolka 2#..\..\myMusic\Noten\Blätter\Stachuspolka 2.pdf#</Speicherort>
    <img>Cards_Export/card_520.png</img>
  </Notentisch>
  <Notentisch>
    <NotID>525</NotID>
    <ArbeitsStatus>Zurück</ArbeitsStatus>
    <Speicherort>Gipfelstürmer#..\..\myMusic\Noten\Blätter\Gipfelstürmer.pdf#</Speicherort>
    <img>Cards_Export/card_525.png</img>
  </Notentisch>
  <Notentisch>
    <NotID>526</NotID>
    <ArbeitsStatus>neueIdee</ArbeitsStatus>
    <Speicherort>everybody.pdf#C:\Users\User\OneDrive\myMusic\Noten\Blätter\everybody.pdf#</Speicherort>
    <img>Cards_Export/card_526.png</img>
  </Notentisch>
</dataroot>